mcp_server_bigquery/__init__.py
mcp_server_bigquery/server.py
mcp_server_bigquery-0.3.1.dist-info/METADATA
mcp_server_bigquery-0.3.1.dist-info/WHEEL
mcp_server_bigquery-0.3.1.dist-info/entry_points.txt
mcp_server_bigquery-0.3.1.dist-info/licenses/LICENSE
mcp_server_bigquery-0.3.1.dist-info/RECORD
